phoenixc2/__init__.py
phoenixc2/__main__.py
phoenixc2/client/__init__.py
phoenixc2/client/__main__.py
phoenixc2/client/cli.py
phoenixc2/client/data/config.toml
phoenixc2/client/models/__init__.py
phoenixc2/client/models/server.py
phoenixc2/client/models/user.py
phoenixc2/client/widgets.py
phoenixc2/development/__init__.py
phoenixc2/development/database.py
phoenixc2/development/module.py
phoenixc2/development/plugin.py
phoenixc2/development/stager.py
phoenixc2/development/testing.py
phoenixc2/server/__init__.py
phoenixc2/server/__main__.py
phoenixc2/server/args.py
phoenixc2/server/bypasses/__init__.py
phoenixc2/server/bypasses/base.py
phoenixc2/server/bypasses/encoders/base64.py
phoenixc2/server/bypasses/encoders/hex.py
phoenixc2/server/bypasses/encoders/url.py
phoenixc2/server/commander/__init__.py
phoenixc2/server/commander/commander.py
phoenixc2/server/commander/services.py
phoenixc2/server/data/configs/default.toml
phoenixc2/server/data/configs/template.toml
phoenixc2/server/data/configs/testing.toml
phoenixc2/server/database/__init__.py
phoenixc2/server/database/base.py
phoenixc2/server/database/engine.py
phoenixc2/server/database/models/association.py
phoenixc2/server/database/models/bypass_chains.py
phoenixc2/server/database/models/credentials.py
phoenixc2/server/database/models/devices.py
phoenixc2/server/database/models/listeners.py
phoenixc2/server/database/models/logs.py
phoenixc2/server/database/models/operations.py
phoenixc2/server/database/models/stagers.py
phoenixc2/server/database/models/tasks.py
phoenixc2/server/database/models/users.py
phoenixc2/server/kits/__init__.py
phoenixc2/server/kits/example/KIT.MD
phoenixc2/server/kits/example/__init__.py
phoenixc2/server/kits/example/handler.py
phoenixc2/server/kits/example/listener.py
phoenixc2/server/kits/example/payloads/python.j2
phoenixc2/server/kits/example/stager.py
phoenixc2/server/kits/handler_base.py
phoenixc2/server/kits/http_reverse/KIT.MD
phoenixc2/server/kits/http_reverse/__init__.py
phoenixc2-1.1.dist-info/LICENSE
phoenixc2-1.1.dist-info/METADATA
phoenixc2-1.1.dist-info/WHEEL
phoenixc2-1.1.dist-info/entry_points.txt
phoenixc2-1.1.dist-info/RECORD
