Metadata-Version: 2.1
Name: phoenixc2
Version: 1.1
Summary: A C2 Framework for Red Team Operations
License: LICENSE
Keywords: pentesting,c2,redteam,hacking
Author: Screamz2k
Requires-Python: >=3.11
Classifier: Development Status :: 3 - Alpha
Classifier: Framework :: Flask
Classifier: Intended Audience :: Developers
Classifier: License :: OSI Approved :: BSD License
Classifier: License :: Other/Proprietary License
Classifier: Natural Language :: English
Classifier: Programming Language :: Python :: 3
Classifier: Programming Language :: Python :: 3.11
Classifier: Programming Language :: Python :: 3
Classifier: Topic :: Security
Provides-Extra: mysql
Provides-Extra: postgresql
Requires-Dist: bleach
Requires-Dist: flask
Requires-Dist: markdown
Requires-Dist: mysqlclient ; extra == "mysql"
Requires-Dist: psutil
Requires-Dist: psycopg2 ; extra == "postgresql"
Requires-Dist: pyOpenSSL
Requires-Dist: pystyle
Requires-Dist: requests
Requires-Dist: rich
Requires-Dist: sqlalchemy (==2.0.8)
Requires-Dist: tomli_w
Project-URL: documentation, https://screamz2k.gitbook.io/phoenixc2/
Project-URL: homepage, https://github.com/Screamz2k/PhoenixC2
Project-URL: repository, https://github.com/Screamz2k/PhoenixC2
